hydrosim_sdk/__init__.py
hydrosim_sdk/ctypes_json.py
hydrosim_sdk/drivers.py
hydrosim_sdk/hydrosim_command_structs.py
hydrosim_sdk/hydrosim_commands.py
hydrosim_sdk/hydrosim_file.py
hydrosim_sdk/hydrosim_sdk.py
hydrosim_sdk/hydrosim_struct_base.py
hydrosim_sdk/hydrosim_structs.py
hydrosim_sdk-1.4.0.dist-info/LICENSE
hydrosim_sdk-1.4.0.dist-info/METADATA
hydrosim_sdk-1.4.0.dist-info/WHEEL
hydrosim_sdk-1.4.0.dist-info/top_level.txt
hydrosim_sdk-1.4.0.dist-info/RECORD
