Metadata-Version: 2.2
Name: hydrosim_sdk
Version: 1.4.0
Summary: HydroSim Shared Memory SDK
Home-page: https://gitlab.com/hydrosim/shared-memory-api/hydrosim-sdk-python
License: MIT
Classifier: Intended Audience :: Developers
Classifier: License :: OSI Approved :: MIT License
Classifier: Programming Language :: Python
Classifier: Programming Language :: Python :: 3.9
Classifier: Programming Language :: Python :: 3.10
Classifier: Operating System :: Microsoft :: Windows
Classifier: Operating System :: POSIX :: Linux
Requires-Python: >=3.9
License-File: LICENSE
Requires-Dist: dtypes
Requires-Dist: pywin32; os_name == "nt"
Dynamic: classifier
Dynamic: description
Dynamic: description-content-type
Dynamic: home-page
Dynamic: license
Dynamic: requires-dist
Dynamic: requires-python
Dynamic: summary
